media_tools/__init__.py
media_tools/video/__init__.py
media_tools/video/converter.py
media_tools/video/options.py
gagip_media_tools-0.1.1.dist-info/METADATA
gagip_media_tools-0.1.1.dist-info/WHEEL
gagip_media_tools-0.1.1.dist-info/top_level.txt
gagip_media_tools-0.1.1.dist-info/RECORD
