Metadata-Version: 2.4
Name: gagip-media-tools
Version: 0.1.1
Summary: 미디어 도구 모음
Author-email: gagip <y02645@gmail.com>
License: MIT
Requires-Python: >=3.12
Requires-Dist: ffmpeg-python>=0.2.0
Requires-Dist: pre-commit>=4.2.0
